SemanticFieldDefinitionGenerator/__init__.py
SemanticFieldDefinitionGenerator/generator.py
SemanticFieldDefinitionGenerator/parser.py
SemanticFieldDefinitionGenerator/semantic_field_util.py
SemanticFieldDefinitionGenerator/templates/inline.handlebars
SemanticFieldDefinitionGenerator/templates/json.handlebars
SemanticFieldDefinitionGenerator/templates/metaphacts.handlebars
SemanticFieldDefinitionGenerator/templates/researchspace.handlebars
SemanticFieldDefinitionGenerator/templates/universal.handlebars
semantic_field_definition_generator-1.5.dist-info/LICENSE
semantic_field_definition_generator-1.5.dist-info/METADATA
semantic_field_definition_generator-1.5.dist-info/WHEEL
semantic_field_definition_generator-1.5.dist-info/entry_points.txt
semantic_field_definition_generator-1.5.dist-info/top_level.txt
semantic_field_definition_generator-1.5.dist-info/RECORD
