Metadata-Version: 2.1
Name: semantic-field-definition-generator
Version: 1.5
Summary: A generator for Field Definitions for ResearchSpace and Metaphacts
Author-email: Robert Casties <casties@mpiwg-berlin.mpg.de>, Florian Kräutli <florian.kraeutli@uzh.ch>
License: Copyright (c) 2018 The Python Packaging Authority
Project-URL: Homepage, https://github.com/robcast/semantic-field-definition-generator
Classifier: Programming Language :: Python :: 3
Classifier: License :: OSI Approved :: MIT License
Classifier: Operating System :: OS Independent
Requires-Python: >=3.7
License-File: LICENSE
Requires-Dist: pybars3
Requires-Dist: PyYAML
Requires-Dist: rdflib
